sidewinder/__init__.py
sidewinder/client.py
sidewinder/config.py
sidewinder/constants.py
sidewinder/security.py
sidewinder/server.py
sidewinder/utils.py
sidewinder/worker.py
sidewinder/parser/__init__.py
sidewinder/parser/query.py
sidewinder/setup/__init__.py
sidewinder/setup/bootstrap.py
sidewinder/setup/build_shards.py
sidewinder/setup/create_duckdb_database_from_parquet.py
sidewinder/setup/data_creation_utils.py
sidewinder/setup/generate_tpch_parquet_data.py
sidewinder/setup/mtls_utilities.py
sidewinder/setup/tls_utilities.py
sidewinder/setup/config/__init__.py
sidewinder/setup/config/ssb_shard_generation_queries.yaml
sidewinder/setup/config/tpch_shard_generation_queries.yaml
sidewinder_db-0.0.73.dist-info/LICENSE
sidewinder_db-0.0.73.dist-info/METADATA
sidewinder_db-0.0.73.dist-info/WHEEL
sidewinder_db-0.0.73.dist-info/entry_points.txt
sidewinder_db-0.0.73.dist-info/top_level.txt
sidewinder_db-0.0.73.dist-info/RECORD
