Metadata-Version: 2.1
Name: sidewinder-db
Version: 0.0.73
Summary: A Python-based Distributed Database
Author-email: Philip Moore <prmoore77@hotmail.com>
License: MIT License
Project-URL: Homepage, https://github.com/prmoore77/sidewinder
Keywords: sidwinder,sidewinder-db,database,distributed,shard
Classifier: License :: OSI Approved :: MIT License
Classifier: Programming Language :: Python
Classifier: Programming Language :: Python :: 3
Requires-Python: >=3.10
License-File: LICENSE
Requires-Dist: boto3==1.35.*
Requires-Dist: botocore==1.35.*
Requires-Dist: click==8.1.*
Requires-Dist: codetiming==1.4.*
Requires-Dist: duckdb==1.1.*
Requires-Dist: duckdb-engine==0.13.*
Requires-Dist: jmespath==1.0.*
Requires-Dist: mgzip==0.2.*
Requires-Dist: munch==4.0.*
Requires-Dist: numpy==2.1.*
Requires-Dist: pandas==2.2.*
Requires-Dist: pglast==6.3.*
Requires-Dist: psutil==6.0.*
Requires-Dist: pyarrow==17.0.0
Requires-Dist: python-dateutil==2.9.*
Requires-Dist: pytz==2024.*
Requires-Dist: PyYAML==6.0.*
Requires-Dist: s3transfer==0.10.*
Requires-Dist: six==1.16.*
Requires-Dist: SQLAlchemy==2.0.*
Requires-Dist: sqlparse==0.5.*
Requires-Dist: urllib3==2.2.*
Requires-Dist: websockets==13.0.*
Requires-Dist: zstandard==0.23.*
Requires-Dist: python-dotenv==1.0.*
Requires-Dist: cryptography==43.0.*
Requires-Dist: requests==2.32.*
Provides-Extra: dev
Requires-Dist: bumpver; extra == "dev"
Requires-Dist: pip-tools; extra == "dev"
Requires-Dist: pytest; extra == "dev"
